[
  {
    "id": "wa_120363307180171348@g.us_1772778035005",
    "source": "whatsapp",
    "child": "ran",
    "group": "הורי כיתה יא׳7",
    "from": "מחנכת יא7",
    "text": "שלום הורים, בשבוע הבא יתקיים מפגש הורים ומורים ביום שלישי בשעה 19:00. נא לאשר הגעה.",
    "body": "שלום הורים, בשבוע הבא יתקיים מפגש הורים ומורים ביום שלישי בשעה 19:00. נא לאשר הגעה.",
    "time": "2026-03-06T06:20:35.005598+00:00",
    "pinned": false,
    "read": false,
    "priority": "high"
  },
  {
    "id": "wa_120363280306116883@g.us_1772778035006",
    "source": "whatsapp",
    "child": "alon",
    "group": "כיתה ב׳ תשפ״ו",
    "from": "מחנכת ב׳",
    "text": "חוזר דחוף: מחר יש יום ספורט לכיתה ב׳. יש להביא בגדי ספורט ונעליים מתאימות.",
    "body": "חוזר דחוף: מחר יש יום ספורט לכיתה ב׳. יש להביא בגדי ספורט ונעליים מתאימות.",
    "time": "2026-03-06T06:20:35.006117+00:00",
    "pinned": false,
    "read": false,
    "priority": "urgent"
  },
  {
    "id": "wa_972528618633-1597665940@g.us_1772778035006",
    "source": "whatsapp",
    "child": "noga",
    "group": "כיתה ו׳2",
    "from": "ועד הורים ו2",
    "text": "ילדים יקרים, השבוע נלמד על פורים. נשמח אם כל ילד יביא תחפושת ביום חמישי.",
    "body": "ילדים יקרים, השבוע נלמד על פורים. נשמח אם כל ילד יביא תחפושת ביום חמישי.",
    "time": "2026-03-06T06:20:35.006336+00:00",
    "pinned": false,
    "read": false,
    "priority": "normal"
  },
  {
    "id": "wa_120363151256867420@g.us_1772778035006",
    "source": "whatsapp",
    "child": "itai",
    "group": "הורי כיתה ט׳3",
    "from": "מזכירות בית הספר",
    "text": "תזכורת: הגשת טופס אישור הורים לטיול ט׳3 עד יום ראשון.",
    "body": "תזכורת: הגשת טופס אישור הורים לטיול ט׳3 עד יום ראשון.",
    "time": "2026-03-06T06:20:35.006506+00:00",
    "pinned": false,
    "read": false,
    "priority": "high"
  },
  {
    "id": "demo_exam_1",
    "source": "whatsapp",
    "child": "ran",
    "group": "הורי כיתה יא׳7",
    "from": "מחנכת רן",
    "text": "תזכורת: מחר יש מבחן בחשבון לכל הכיתה. נא להכין חומר עזר",
    "body": "תזכורת: מחר יש מבחן בחשבון לכל הכיתה. נא להכין חומר עזר",
    "time": "2026-03-06T12:33:44.190859+00:00",
    "pinned": true,
    "read": false,
    "priority": "urgent",
    "category": "exam",
    "category_label": "מבחן",
    "category_emoji": "📝",
    "wa_reason": "מבחן"
  },
  {
    "id": "demo_cancel_1",
    "source": "whatsapp",
    "child": "alon",
    "group": "כיתה ב׳ תשפ״ו",
    "from": "ועד הורים",
    "text": "ביטול: הטיול לגן חיות ביום חמישי מבוטל עקב מזג האוויר. יום לימודים רגיל",
    "body": "ביטול: הטיול לגן חיות ביום חמישי מבוטל עקב מזג האוויר. יום לימודים רגיל",
    "time": "2026-03-06T12:33:44.220392+00:00",
    "pinned": false,
    "read": false,
    "priority": "high",
    "category": "trip",
    "category_label": "טיול",
    "category_emoji": "🚌",
    "wa_reason": "טיול"
  },
  {
    "id": "demo_task_1",
    "source": "whatsapp",
    "child": "itai",
    "group": "הורי כיתה ט׳3",
    "from": "מזכירות",
    "text": "אישור הורים לטיול ט׳3 נדרש עד יום ראשון בשעה 20:00. קישור לטופס המצורף",
    "body": "אישור הורים לטיול ט׳3 נדרש עד יום ראשון בשעה 20:00. קישור לטופס המצורף",
    "time": "2026-03-06T12:33:44.246265+00:00",
    "pinned": false,
    "read": false,
    "priority": "high",
    "category": "task",
    "category_label": "מטלה",
    "category_emoji": "✅",
    "wa_reason": "אישור"
  },
  {
    "id": "demo_event_1",
    "source": "whatsapp",
    "child": "noga",
    "group": "כיתה ו׳2",
    "from": "מחנכת",
    "text": "יום כיף לכיתה ו׳2 יתקיים ביום שישי. יש להביא כסף לאוכל ובגדים נוחים",
    "body": "יום כיף לכיתה ו׳2 יתקיים ביום שישי. יש להביא כסף לאוכל ובגדים נוחים",
    "time": "2026-03-06T12:33:44.272468+00:00",
    "pinned": false,
    "read": false,
    "priority": "high",
    "category": "task",
    "category_label": "מטלה",
    "category_emoji": "✅",
    "wa_reason": "יש להביא"
  },
  {
    "id": "demo_pay_1",
    "source": "whatsapp",
    "child": "alon",
    "group": "שכבה ב׳ לביא",
    "from": "ועד הורים",
    "text": "תשלום עבור ספרי לימוד לשנת הלימודים הבאה — 250 ש״ח. ניתן לשלם דרך האפליקציה",
    "body": "תשלום עבור ספרי לימוד לשנת הלימודים הבאה — 250 ש״ח. ניתן לשלם דרך האפליקציה",
    "time": "2026-03-06T12:33:44.298804+00:00",
    "pinned": false,
    "read": false,
    "priority": "high",
    "category": "payment",
    "category_label": "תשלום",
    "category_emoji": "💳",
    "wa_reason": "תשלום"
  },
  {
    "id": "demo_sched_1",
    "source": "whatsapp",
    "child": "alon",
    "group": "שכבה ב׳ לביא",
    "from": "מחנכת רן",
    "text": "שינוי בלוח השעות ביום שלישי: קיצור יום עד 13:00. תלמידים יוצאים מוקדם",
    "body": "שינוי בלוח השעות ביום שלישי: קיצור יום עד 13:00. תלמידים יוצאים מוקדם",
    "time": "2026-03-06T12:33:44.324846+00:00",
    "pinned": true,
    "read": false,
    "priority": "urgent",
    "category": "cancellation",
    "category_label": "ביטול / שינוי",
    "category_emoji": "🚫",
    "wa_reason": "שינוי"
  }
]